{
  "schemaVersion": 1,
  "workshopId": "2805199049",
  "source": "steam-workshop-config",
  "extractedAt": "2026-07-18T00:43:10+00:00",
  "buildings": [
    {
      "id": "2805199049/Tropicana_Hotel",
      "nameId": null,
      "types": [
        "TYPE_HOTEL"
      ],
      "workers": 150.0,
      "professors": 0,
      "production": {},
      "consumption": {},
      "consumptionPerSecond": {},
      "livingSpace": 0,
      "citizenAbleServe": 7.0,
      "qualityOfLiving": null,
      "attractiveScore": 5.0,
      "storages": {},
      "constructionResources": {},
      "electricWorkerFactors": {},
      "nameStr": "Tropicana Tower Hotel *****",
      "workshopId": "2805199049",
      "modPath": "Tropicana_Hotel"
    }
  ],
  "vehicles": []
}
