{
  "schemaVersion": 1,
  "workshopId": "2474714638",
  "source": "steam-workshop-config",
  "extractedAt": "2026-07-18T07:52:35+00:00",
  "buildings": [],
  "vehicles": [
    {
      "id": "2474714638/1328",
      "category": "workshop",
      "lifespanYears": 0.0,
      "length": 25.55,
      "type": "VEHICLETYPE_SHIP",
      "costRUB": 4300.0,
      "speed": 35.0,
      "powerKW": 220.0,
      "emptyWeight": 26.0,
      "capacity": 66.0,
      "transportType": "RESOURCE_TRANSPORT_GENERAL",
      "from": 1971,
      "to": 2010,
      "countryId": 39009,
      "electric": false,
      "workshopId": "2474714638",
      "modPath": "1328"
    },
    {
      "id": "2474714638/333",
      "category": "workshop",
      "lifespanYears": 0.0,
      "length": 62.69,
      "type": "VEHICLETYPE_SHIP",
      "costRUB": 4300.0,
      "speed": 45.0,
      "powerKW": 1789.0,
      "emptyWeight": 736.0,
      "capacity": 722.0,
      "transportType": "RESOURCE_TRANSPORT_GENERAL",
      "from": 1980,
      "to": 2020,
      "countryId": 39004,
      "electric": false,
      "workshopId": "2474714638",
      "modPath": "333"
    },
    {
      "id": "2474714638/464",
      "category": "workshop",
      "lifespanYears": 0.0,
      "length": 103.54,
      "type": "VEHICLETYPE_SHIP",
      "costRUB": 4300.0,
      "speed": 48.0,
      "powerKW": 2855.0,
      "emptyWeight": 1860.0,
      "capacity": 2732.0,
      "transportType": "RESOURCE_TRANSPORT_GENERAL",
      "from": 1972,
      "to": 2020,
      "countryId": 39004,
      "electric": false,
      "workshopId": "2474714638",
      "modPath": "464"
    },
    {
      "id": "2474714638/MRS80",
      "category": "workshop",
      "lifespanYears": 0.0,
      "length": 18.18,
      "type": "VEHICLETYPE_SHIP",
      "costRUB": 4300.0,
      "speed": 25.0,
      "powerKW": 60.0,
      "emptyWeight": 21.0,
      "capacity": 26.0,
      "transportType": "RESOURCE_TRANSPORT_GENERAL",
      "from": 1954,
      "to": 1981,
      "countryId": 39011,
      "electric": false,
      "workshopId": "2474714638",
      "modPath": "MRS80"
    },
    {
      "id": "2474714638/kutter",
      "category": "workshop",
      "lifespanYears": 0.0,
      "length": 17.4,
      "type": "VEHICLETYPE_SHIP",
      "costRUB": 4300.0,
      "speed": 21.0,
      "powerKW": 59.0,
      "emptyWeight": 18.0,
      "capacity": 24.0,
      "transportType": "RESOURCE_TRANSPORT_GENERAL",
      "from": 1945,
      "to": 1995,
      "countryId": 39004,
      "electric": false,
      "workshopId": "2474714638",
      "modPath": "kutter"
    },
    {
      "id": "2474714638/serie3",
      "category": "workshop",
      "lifespanYears": 0.0,
      "length": 66.25,
      "type": "VEHICLETYPE_SHIP",
      "costRUB": 4300.0,
      "speed": 40.0,
      "powerKW": 677.0,
      "emptyWeight": 291.0,
      "capacity": 600.0,
      "transportType": "RESOURCE_TRANSPORT_GENERAL",
      "from": 1960,
      "to": 1983,
      "countryId": 39004,
      "electric": false,
      "workshopId": "2474714638",
      "modPath": "serie3"
    },
    {
      "id": "2474714638/steamtrawler",
      "category": "workshop",
      "lifespanYears": 0.0,
      "length": 41.13,
      "type": "VEHICLETYPE_SHIP",
      "costUSD": 4300.0,
      "speed": 35.0,
      "powerKW": 360.0,
      "emptyWeight": 104.0,
      "capacity": 266.0,
      "transportType": "RESOURCE_TRANSPORT_GENERAL",
      "from": 1900,
      "to": 1968,
      "countryId": 39041,
      "electric": false,
      "workshopId": "2474714638",
      "modPath": "steamtrawler"
    }
  ]
}
