{
  "schemaVersion": 1,
  "workshopId": "2799608833",
  "source": "steam-workshop-config",
  "extractedAt": "2026-07-18T00:07:17+00:00",
  "buildings": [
    {
      "id": "2799608833/sporthall",
      "nameId": null,
      "types": [
        "TYPE_SPORT"
      ],
      "workers": 20.0,
      "professors": 0,
      "production": {},
      "consumption": {},
      "consumptionPerSecond": {},
      "livingSpace": 0,
      "citizenAbleServe": 5.0,
      "qualityOfLiving": null,
      "attractiveScore": 2.5,
      "storages": {},
      "constructionResources": {},
      "electricWorkerFactors": {},
      "nameStr": "Sports Hall",
      "workshopId": "2799608833",
      "modPath": "sporthall"
    }
  ],
  "vehicles": []
}
