{
  "schemaVersion": 1,
  "workshopId": "3216658252",
  "source": "steam-workshop-config",
  "extractedAt": "2026-07-17T21:35:10+00:00",
  "buildings": [],
  "vehicles": [
    {
      "id": "3216658252/BR218",
      "category": "workshop",
      "lifespanYears": 0.0,
      "length": 15.97,
      "type": "VEHICLETYPE_RAIL_LOCOMOTIVE",
      "costUSD": 1.0,
      "consumption": 0.0,
      "speed": 140.0,
      "powerKW": 1840.0,
      "emptyWeight": 80.0,
      "from": 1960,
      "to": 1981,
      "countryId": 39005,
      "trainGroup": "locomotive",
      "workshopId": "3216658252",
      "modPath": "BR218"
    },
    {
      "id": "3216658252/DBV60",
      "category": "workshop",
      "lifespanYears": 0.0,
      "length": 10.47,
      "type": "VEHICLETYPE_RAIL_LOCOMOTIVE",
      "costUSD": 1.0,
      "consumption": 0.0,
      "speed": 60.0,
      "powerKW": 478.0,
      "emptyWeight": 49.0,
      "from": 1956,
      "to": 1967,
      "countryId": 39005,
      "trainGroup": "locomotive",
      "workshopId": "3216658252",
      "modPath": "DBV60"
    },
    {
      "id": "3216658252/DRV60",
      "category": "workshop",
      "lifespanYears": 0.0,
      "length": 10.72,
      "type": "VEHICLETYPE_RAIL_LOCOMOTIVE",
      "costRUB": 1.0,
      "consumption": 0.0,
      "speed": 60.0,
      "powerKW": 478.0,
      "emptyWeight": 60.0,
      "from": 1959,
      "to": 1982,
      "countryId": 39004,
      "trainGroup": "locomotive",
      "workshopId": "3216658252",
      "modPath": "DRV60"
    },
    {
      "id": "3216658252/V180",
      "category": "workshop",
      "lifespanYears": 0.0,
      "length": 19.48,
      "type": "VEHICLETYPE_RAIL_LOCOMOTIVE",
      "costRUB": 1.0,
      "consumption": 0.0,
      "speed": 120.0,
      "powerKW": 1766.0,
      "emptyWeight": 93.0,
      "from": 1959,
      "to": 1970,
      "countryId": 39004,
      "trainGroup": "locomotive",
      "workshopId": "3216658252",
      "modPath": "V180"
    },
    {
      "id": "3216658252/V188",
      "category": "workshop",
      "lifespanYears": 0.0,
      "length": 11.22,
      "type": "VEHICLETYPE_RAIL_LOCOMOTIVE",
      "costUSD": 1.0,
      "consumption": 0.0,
      "speed": 75.0,
      "powerKW": 691.0,
      "emptyWeight": 73.5,
      "from": 1941,
      "to": 1951,
      "countryId": 39003,
      "trainGroup": "locomotive",
      "workshopId": "3216658252",
      "modPath": "V188"
    },
    {
      "id": "3216658252/V200",
      "category": "workshop",
      "lifespanYears": 0.0,
      "length": 18.38,
      "type": "VEHICLETYPE_RAIL_LOCOMOTIVE",
      "costUSD": 1.0,
      "consumption": 0.0,
      "speed": 140.0,
      "powerKW": 1618.0,
      "emptyWeight": 80.0,
      "from": 1953,
      "to": 1966,
      "countryId": 39005,
      "trainGroup": "locomotive",
      "workshopId": "3216658252",
      "modPath": "V200"
    },
    {
      "id": "3216658252/V80",
      "category": "workshop",
      "lifespanYears": 0.0,
      "length": 12.39,
      "type": "VEHICLETYPE_RAIL_LOCOMOTIVE",
      "costUSD": 1.0,
      "consumption": 0.0,
      "speed": 100.0,
      "powerKW": 809.0,
      "emptyWeight": 58.0,
      "from": 1952,
      "to": 1965,
      "countryId": 39005,
      "trainGroup": "locomotive",
      "workshopId": "3216658252",
      "modPath": "V80"
    }
  ]
}
