{
  "schemaVersion": 1,
  "workshopId": "3716438911",
  "source": "steam-workshop-config",
  "extractedAt": "2026-07-18T21:23:21+00:00",
  "buildings": [],
  "vehicles": [
    {
      "id": "3716438911/AstraFCaravan",
      "category": "workshop",
      "lifespanYears": 0.0,
      "type": "VEHICLETYPE_ROAD",
      "descriptionId": 5439,
      "costUSD": 1.0,
      "consumption": 0.0,
      "speed": 149.0,
      "powerKW": 44.0,
      "emptyWeight": 1.09,
      "capacity": 5.0,
      "transportType": "RESOURCE_TRANSPORT_PASSANGER",
      "from": 1992,
      "to": 1995,
      "countryId": 39003,
      "roadRecipeBranch": "ordinary",
      "workshopId": "3716438911",
      "modPath": "AstraFCaravan"
    },
    {
      "id": "3716438911/AstraFCaravan_FL",
      "category": "workshop",
      "lifespanYears": 0.0,
      "type": "VEHICLETYPE_ROAD",
      "descriptionId": 5439,
      "costUSD": 1.0,
      "consumption": 0.0,
      "speed": 160.0,
      "powerKW": 50.0,
      "emptyWeight": 1.13,
      "capacity": 5.0,
      "transportType": "RESOURCE_TRANSPORT_PASSANGER",
      "from": 1994,
      "to": 2003,
      "countryId": 39003,
      "roadRecipeBranch": "ordinary",
      "workshopId": "3716438911",
      "modPath": "AstraFCaravan_FL"
    },
    {
      "id": "3716438911/AstraFCaravan_P",
      "category": "workshop",
      "lifespanYears": 0.0,
      "type": "VEHICLETYPE_ROAD",
      "descriptionId": 5439,
      "costUSD": 1.0,
      "consumption": 0.0,
      "speed": 168.0,
      "powerKW": 55.0,
      "emptyWeight": 1.1,
      "capacity": 5.0,
      "transportType": "RESOURCE_TRANSPORT_PASSANGER",
      "from": 1992,
      "to": 1995,
      "countryId": 39003,
      "roadRecipeBranch": "ordinary",
      "workshopId": "3716438911",
      "modPath": "AstraFCaravan_P"
    },
    {
      "id": "3716438911/AstraFCaravan_P_FL",
      "category": "workshop",
      "lifespanYears": 0.0,
      "type": "VEHICLETYPE_ROAD",
      "descriptionId": 5439,
      "costUSD": 1.0,
      "consumption": 0.0,
      "speed": 198.0,
      "powerKW": 92.0,
      "emptyWeight": 1.26,
      "capacity": 5.0,
      "transportType": "RESOURCE_TRANSPORT_PASSANGER",
      "from": 1994,
      "to": 2004,
      "countryId": 39003,
      "roadRecipeBranch": "ordinary",
      "workshopId": "3716438911",
      "modPath": "AstraFCaravan_P_FL"
    },
    {
      "id": "3716438911/AstraFVan",
      "category": "workshop",
      "lifespanYears": 0.0,
      "type": "VEHICLETYPE_ROAD",
      "descriptionId": 5439,
      "costUSD": 1.0,
      "consumption": 0.0,
      "speed": 149.0,
      "powerKW": 44.0,
      "emptyWeight": 1.03,
      "capacity": 0.6,
      "transportType": "RESOURCE_TRANSPORT_COVERED",
      "from": 1992,
      "to": 1995,
      "countryId": 39003,
      "roadRecipeBranch": "ordinary",
      "workshopId": "3716438911",
      "modPath": "AstraFVan"
    },
    {
      "id": "3716438911/AstraFVan_FL",
      "category": "workshop",
      "lifespanYears": 0.0,
      "type": "VEHICLETYPE_ROAD",
      "descriptionId": 5439,
      "costUSD": 1.0,
      "consumption": 0.0,
      "speed": 168.0,
      "powerKW": 60.0,
      "emptyWeight": 1.08,
      "capacity": 0.6,
      "transportType": "RESOURCE_TRANSPORT_COVERED",
      "from": 1994,
      "to": 2004,
      "countryId": 39003,
      "roadRecipeBranch": "ordinary",
      "workshopId": "3716438911",
      "modPath": "AstraFVan_FL"
    }
  ]
}
