{
  "schemaVersion": 1,
  "workshopId": "3016396205",
  "source": "steam-workshop-config",
  "extractedAt": "2026-07-18T05:48:46+00:00",
  "buildings": [
    {
      "id": "3016396205/1",
      "nameId": null,
      "types": [
        "TYPE_CITYHALL"
      ],
      "workers": 100.0,
      "professors": 0,
      "production": {},
      "consumption": {},
      "consumptionPerSecond": {},
      "livingSpace": 0,
      "citizenAbleServe": 0,
      "qualityOfLiving": null,
      "attractiveScore": null,
      "storages": {},
      "constructionResources": {},
      "electricWorkerFactors": {},
      "nameStr": "Rail admin building",
      "workshopId": "3016396205",
      "modPath": "1"
    },
    {
      "id": "3016396205/2",
      "nameId": null,
      "types": [
        "TYPE_ATTRACTION"
      ],
      "workers": 50.0,
      "professors": 0,
      "production": {},
      "consumption": {},
      "consumptionPerSecond": {},
      "livingSpace": 0,
      "citizenAbleServe": 12.0,
      "qualityOfLiving": null,
      "attractiveScore": 2.0,
      "storages": {},
      "constructionResources": {},
      "electricWorkerFactors": {},
      "nameStr": "Railway museum",
      "workshopId": "3016396205",
      "modPath": "2"
    },
    {
      "id": "3016396205/3",
      "nameId": null,
      "types": [
        "TYPE_SHOP",
        "SUBTYPE_RESTAURANT"
      ],
      "workers": 10.0,
      "professors": 0,
      "production": {},
      "consumption": {},
      "consumptionPerSecond": {},
      "livingSpace": 0,
      "citizenAbleServe": 20.0,
      "qualityOfLiving": null,
      "attractiveScore": 2.0,
      "storages": {},
      "constructionResources": {},
      "electricWorkerFactors": {},
      "nameStr": "Railway restaurant",
      "workshopId": "3016396205",
      "modPath": "3"
    },
    {
      "id": "3016396205/4",
      "nameId": null,
      "types": [
        "TYPE_ATTRACTION"
      ],
      "workers": 20.0,
      "professors": 0,
      "production": {},
      "consumption": {},
      "consumptionPerSecond": {},
      "livingSpace": 0,
      "citizenAbleServe": 5.0,
      "qualityOfLiving": null,
      "attractiveScore": 3.5,
      "storages": {},
      "constructionResources": {},
      "electricWorkerFactors": {},
      "nameStr": "Historic rail boiler room",
      "workshopId": "3016396205",
      "modPath": "4"
    },
    {
      "id": "3016396205/5",
      "nameId": null,
      "types": [
        "TYPE_CITYHALL"
      ],
      "workers": 100.0,
      "professors": 0,
      "production": {},
      "consumption": {},
      "consumptionPerSecond": {},
      "livingSpace": 0,
      "citizenAbleServe": 0,
      "qualityOfLiving": null,
      "attractiveScore": null,
      "storages": {},
      "constructionResources": {},
      "electricWorkerFactors": {},
      "nameStr": "Rail admin building",
      "workshopId": "3016396205",
      "modPath": "5"
    },
    {
      "id": "3016396205/6",
      "nameId": null,
      "types": [
        "TYPE_ATTRACTION"
      ],
      "workers": 50.0,
      "professors": 0,
      "production": {},
      "consumption": {},
      "consumptionPerSecond": {},
      "livingSpace": 0,
      "citizenAbleServe": 12.0,
      "qualityOfLiving": null,
      "attractiveScore": 2.0,
      "storages": {},
      "constructionResources": {},
      "electricWorkerFactors": {},
      "nameStr": "Railway museum",
      "workshopId": "3016396205",
      "modPath": "6"
    },
    {
      "id": "3016396205/7",
      "nameId": null,
      "types": [
        "TYPE_SHOP",
        "SUBTYPE_RESTAURANT"
      ],
      "workers": 10.0,
      "professors": 0,
      "production": {},
      "consumption": {},
      "consumptionPerSecond": {},
      "livingSpace": 0,
      "citizenAbleServe": 20.0,
      "qualityOfLiving": null,
      "attractiveScore": 2.0,
      "storages": {},
      "constructionResources": {},
      "electricWorkerFactors": {},
      "nameStr": "Railway restaurant",
      "workshopId": "3016396205",
      "modPath": "7"
    }
  ],
  "vehicles": []
}
