{
  "schemaVersion": 1,
  "workshopId": "3345766947",
  "source": "steam-workshop-config",
  "extractedAt": "2026-07-18T01:06:43+00:00",
  "buildings": [
    {
      "id": "3345766947/LargeCov",
      "nameId": null,
      "types": [
        "TYPE_STORAGE"
      ],
      "workers": 0,
      "professors": 0,
      "production": {},
      "consumption": {},
      "consumptionPerSecond": {},
      "livingSpace": 0,
      "citizenAbleServe": 0,
      "qualityOfLiving": null,
      "attractiveScore": null,
      "storages": {
        "RESOURCE_TRANSPORT_OPEN": 6200.0
      },
      "constructionResources": {},
      "electricWorkerFactors": {},
      "nameStr": "Large Covered Open Storage",
      "workshopId": "3345766947",
      "modPath": "LargeCov"
    }
  ],
  "vehicles": []
}
