{
  "schemaVersion": 1,
  "workshopId": "2568863769",
  "source": "steam-workshop-config",
  "extractedAt": "2026-07-18T19:34:48+00:00",
  "buildings": [],
  "vehicles": [
    {
      "id": "2568863769/1",
      "category": "workshop",
      "lifespanYears": 0.0,
      "length": 3.66,
      "type": "VEHICLETYPE_ROAD",
      "costUSD": 1.0,
      "consumption": 0.0,
      "speed": 90.0,
      "powerKW": 17.0,
      "emptyWeight": 0.6,
      "capacity": 4.0,
      "transportType": "RESOURCE_TRANSPORT_PASSANGER",
      "from": 1974,
      "to": 1992,
      "roadRecipeBranch": "ordinary",
      "workshopId": "2568863769",
      "modPath": "1"
    }
  ]
}
