{
  "schemaVersion": 1,
  "workshopId": "1994837114",
  "source": "steam-workshop-config",
  "extractedAt": "2026-07-18T08:13:42+00:00",
  "buildings": [],
  "vehicles": [
    {
      "id": "1994837114/1",
      "category": "workshop",
      "lifespanYears": 0.0,
      "length": 4.77,
      "type": "VEHICLETYPE_ROAD",
      "costUSD": 4300.0,
      "consumption": 0.0,
      "speed": 130.0,
      "powerKW": 140.0,
      "emptyWeight": 2.1,
      "capacity": 9.0,
      "transportType": "RESOURCE_TRANSPORT_PASSANGER",
      "from": 1975,
      "to": 1991,
      "countryId": 39018,
      "roadRecipeBranch": "ordinary",
      "workshopId": "1994837114",
      "modPath": "1"
    },
    {
      "id": "1994837114/2",
      "category": "workshop",
      "lifespanYears": 0.0,
      "length": 4.77,
      "type": "VEHICLETYPE_ROAD",
      "costUSD": 4300.0,
      "consumption": 0.0,
      "speed": 130.0,
      "powerKW": 140.0,
      "emptyWeight": 2.1,
      "capacity": 1.6,
      "transportType": "RESOURCE_TRANSPORT_COVERED",
      "from": 1975,
      "to": 1991,
      "countryId": 39018,
      "roadRecipeBranch": "ordinary",
      "workshopId": "1994837114",
      "modPath": "2"
    },
    {
      "id": "1994837114/3",
      "category": "workshop",
      "lifespanYears": 0.0,
      "length": 6.6,
      "type": "VEHICLETYPE_ROAD",
      "costUSD": 4300.0,
      "speed": 100.0,
      "powerKW": 120.0,
      "emptyWeight": 2.3,
      "capacity": 4.1,
      "transportType": "RESOURCE_TRANSPORT_COVERED",
      "from": 1975,
      "to": 1991,
      "countryId": 39018,
      "roadRecipeBranch": "ordinary",
      "workshopId": "1994837114",
      "modPath": "3"
    },
    {
      "id": "1994837114/4",
      "category": "workshop",
      "lifespanYears": 0.0,
      "length": 6.6,
      "type": "VEHICLETYPE_ROAD",
      "costUSD": 4300.0,
      "speed": 100.0,
      "powerKW": 120.0,
      "emptyWeight": 2.3,
      "capacity": 4.1,
      "transportType": "RESOURCE_TRANSPORT_COOLER",
      "from": 1975,
      "to": 1991,
      "countryId": 39018,
      "roadRecipeBranch": "ordinary",
      "workshopId": "1994837114",
      "modPath": "4"
    },
    {
      "id": "1994837114/5",
      "category": "workshop",
      "lifespanYears": 0.0,
      "length": 5.97,
      "type": "VEHICLETYPE_ROAD",
      "costUSD": 4300.0,
      "speed": 100.0,
      "powerKW": 120.0,
      "emptyWeight": 2.2,
      "capacity": 3.7,
      "transportType": "RESOURCE_TRANSPORT_OPEN",
      "from": 1975,
      "to": 1991,
      "countryId": 39018,
      "roadRecipeBranch": "ordinary",
      "workshopId": "1994837114",
      "modPath": "5"
    }
  ]
}
