{
  "schemaVersion": 1,
  "workshopId": "3569694576",
  "source": "steam-workshop-config",
  "extractedAt": "2026-07-18T19:46:36+00:00",
  "buildings": [],
  "vehicles": [
    {
      "id": "3569694576/DongFeng12",
      "category": "workshop",
      "lifespanYears": 0.0,
      "length": 20.04,
      "type": "VEHICLETYPE_RAIL_LOCOMOTIVE",
      "costRUB": 4300.0,
      "speed": 100.0,
      "powerKW": 1985.0,
      "emptyWeight": 138.0,
      "trainGroup": "locomotive",
      "from": 1997,
      "to": 9999,
      "countryId": 39042,
      "electric": false,
      "workshopId": "3569694576",
      "modPath": "DongFeng12"
    },
    {
      "id": "3569694576/DongFeng2",
      "category": "workshop",
      "lifespanYears": 0.0,
      "length": 16.61,
      "type": "VEHICLETYPE_RAIL_LOCOMOTIVE",
      "costRUB": 4300.0,
      "speed": 95.3,
      "powerKW": 650.0,
      "emptyWeight": 113.0,
      "trainGroup": "locomotive",
      "from": 1964,
      "to": 1986,
      "countryId": 39042,
      "electric": false,
      "workshopId": "3569694576",
      "modPath": "DongFeng2"
    },
    {
      "id": "3569694576/DongFeng5",
      "category": "workshop",
      "lifespanYears": 0.0,
      "length": 18.21,
      "type": "VEHICLETYPE_RAIL_LOCOMOTIVE",
      "costRUB": 4300.0,
      "speed": 80.0,
      "powerKW": 930.0,
      "emptyWeight": 135.0,
      "trainGroup": "locomotive",
      "from": 1976,
      "to": 2006,
      "countryId": 39042,
      "electric": false,
      "workshopId": "3569694576",
      "modPath": "DongFeng5"
    },
    {
      "id": "3569694576/DongFeng7",
      "category": "workshop",
      "lifespanYears": 0.0,
      "length": 18.49,
      "type": "VEHICLETYPE_RAIL_LOCOMOTIVE",
      "costRUB": 4300.0,
      "speed": 100.0,
      "powerKW": 1180.0,
      "emptyWeight": 135.0,
      "trainGroup": "locomotive",
      "from": 1982,
      "to": 1997,
      "countryId": 39042,
      "electric": false,
      "workshopId": "3569694576",
      "modPath": "DongFeng7"
    }
  ]
}
