{
  "schemaVersion": 1,
  "workshopId": "1848122646",
  "source": "steam-workshop-config",
  "extractedAt": "2026-07-18T08:11:23+00:00",
  "buildings": [],
  "vehicles": [
    {
      "id": "1848122646/Tram_T3_PTG_DOWN",
      "category": "workshop",
      "lifespanYears": 0.0,
      "length": 14.81,
      "type": "VEHICLETYPE_RAIL_LOCOMOTIVE",
      "descriptionId": 5126,
      "costRUB": 4300.0,
      "powerKW": 160.0,
      "emptyWeight": 16.6,
      "trainGroup": "tram",
      "speed": 65.0,
      "capacity": 86.0,
      "transportType": "RESOURCE_TRANSPORT_PASSANGER",
      "from": 1962,
      "to": 3000,
      "countryId": 39000,
      "electric": true,
      "workshopId": "1848122646",
      "modPath": "Tram_T3_PTG_DOWN"
    },
    {
      "id": "1848122646/Tram_T3_PTG_UP",
      "category": "workshop",
      "lifespanYears": 0.0,
      "length": 14.81,
      "type": "VEHICLETYPE_RAIL_LOCOMOTIVE",
      "descriptionId": 5126,
      "costRUB": 4300.0,
      "powerKW": 160.0,
      "emptyWeight": 16.6,
      "trainGroup": "tram",
      "speed": 65.0,
      "capacity": 86.0,
      "transportType": "RESOURCE_TRANSPORT_PASSANGER",
      "from": 1962,
      "to": 3000,
      "countryId": 39000,
      "electric": true,
      "workshopId": "1848122646",
      "modPath": "Tram_T3_PTG_UP"
    },
    {
      "id": "1848122646/Tramwaj_Funkcni",
      "category": "workshop",
      "trainSet": [
        "1848122646/Tramwaj_Funkcni_Stred"
      ],
      "lifespanYears": 0.0,
      "length": 11.52,
      "type": "VEHICLETYPE_RAIL_LOCOMOTIVE",
      "descriptionId": 5366,
      "costRUB": 4300.0,
      "powerKW": 180.0,
      "emptyWeight": 18.4,
      "speed": 65.0,
      "trainGroup": "tram",
      "capacity": 125.0,
      "transportType": "RESOURCE_TRANSPORT_PASSANGER",
      "from": 1998,
      "to": 3000,
      "electric": true,
      "workshopId": "1848122646",
      "modPath": "Tramwaj_Funkcni"
    },
    {
      "id": "1848122646/Tramwaj_Funkcni-kopie",
      "category": "workshop",
      "trainSet": [
        "1848122646/Tramwaj_Funkcni_Stred-kopie"
      ],
      "lifespanYears": 0.0,
      "length": 11.52,
      "type": "VEHICLETYPE_RAIL_LOCOMOTIVE",
      "descriptionId": 5366,
      "costRUB": 4300.0,
      "powerKW": 180.0,
      "emptyWeight": 18.4,
      "speed": 65.0,
      "trainGroup": "tram",
      "capacity": 125.0,
      "transportType": "RESOURCE_TRANSPORT_PASSANGER",
      "from": 1998,
      "to": 3000,
      "electric": true,
      "workshopId": "1848122646",
      "modPath": "Tramwaj_Funkcni-kopie"
    },
    {
      "id": "1848122646/Tramwaj_Funkcni_Stred",
      "category": "workshop",
      "lifespanYears": 0.0,
      "length": 8.32,
      "type": "VEHICLETYPE_RAIL_VAGON",
      "descriptionId": 5366,
      "costRUB": 4300.0,
      "emptyWeight": 1.0,
      "speed": 65.0,
      "trainGroup": "tram",
      "capacity": 1.0,
      "transportType": "RESOURCE_TRANSPORT_PASSANGER",
      "from": 1985,
      "to": 2003,
      "countryId": 39000,
      "workshopId": "1848122646",
      "modPath": "Tramwaj_Funkcni_Stred"
    },
    {
      "id": "1848122646/Tramwaj_Funkcni_Stred-kopie",
      "category": "workshop",
      "lifespanYears": 0.0,
      "length": 8.32,
      "type": "VEHICLETYPE_RAIL_VAGON",
      "descriptionId": 5366,
      "costRUB": 4300.0,
      "emptyWeight": 1.0,
      "speed": 65.0,
      "trainGroup": "tram",
      "capacity": 1.0,
      "transportType": "RESOURCE_TRANSPORT_PASSANGER",
      "from": 1985,
      "to": 2003,
      "countryId": 39000,
      "workshopId": "1848122646",
      "modPath": "Tramwaj_Funkcni_Stred-kopie"
    },
    {
      "id": "1848122646/Tramwaj_Funkcni_Zadek",
      "category": "workshop",
      "lifespanYears": 0.0,
      "length": 11.52,
      "type": "VEHICLETYPE_RAIL_LOCOMOTIVE",
      "descriptionId": 5366,
      "costRUB": 4300.0,
      "powerKW": 180.0,
      "emptyWeight": 18.4,
      "speed": 65.0,
      "trainGroup": "tram",
      "capacity": 125.0,
      "transportType": "RESOURCE_TRANSPORT_PASSANGER",
      "from": 1985,
      "to": 2003,
      "countryId": 39000,
      "electric": true,
      "workshopId": "1848122646",
      "modPath": "Tramwaj_Funkcni_Zadek"
    },
    {
      "id": "1848122646/Tramwaj_Funkcni_Zadek-kopie",
      "category": "workshop",
      "lifespanYears": 0.0,
      "length": 11.52,
      "type": "VEHICLETYPE_RAIL_LOCOMOTIVE",
      "descriptionId": 5366,
      "costRUB": 4300.0,
      "powerKW": 180.0,
      "emptyWeight": 18.4,
      "speed": 65.0,
      "trainGroup": "tram",
      "capacity": 125.0,
      "transportType": "RESOURCE_TRANSPORT_PASSANGER",
      "from": 1985,
      "to": 2003,
      "countryId": 39000,
      "electric": true,
      "workshopId": "1848122646",
      "modPath": "Tramwaj_Funkcni_Zadek-kopie"
    }
  ]
}
