{
  "schemaVersion": 1,
  "workshopId": "3171531012",
  "source": "steam-workshop-config",
  "extractedAt": "2026-07-18T20:55:50+00:00",
  "buildings": [],
  "vehicles": [
    {
      "id": "3171531012/FP",
      "category": "workshop",
      "lifespanYears": 0.0,
      "length": 10.56,
      "type": "VEHICLETYPE_RAIL_VAGON",
      "descriptionId": 5419,
      "costRUB": 4300.0,
      "speed": 50.0,
      "trainGroup": "tram",
      "capacity": 81.0,
      "transportType": "RESOURCE_TRANSPORT_PASSANGER",
      "from": 1956,
      "to": 1965,
      "countryId": 39007,
      "workshopId": "3171531012",
      "modPath": "FP"
    },
    {
      "id": "3171531012/UV",
      "category": "workshop",
      "lifespanYears": 0.0,
      "length": 13.4,
      "type": "VEHICLETYPE_RAIL_LOCOMOTIVE",
      "descriptionId": 5419,
      "costRUB": 4300.0,
      "powerKW": 148.0,
      "emptyWeight": 19.75,
      "speed": 50.0,
      "trainGroup": "tram",
      "capacity": 101.0,
      "transportType": "RESOURCE_TRANSPORT_PASSANGER",
      "from": 1956,
      "to": 1965,
      "countryId": 39007,
      "electric": true,
      "workshopId": "3171531012",
      "modPath": "UV"
    },
    {
      "id": "3171531012/UV2",
      "category": "workshop",
      "trainSet": [
        "3171531012/UV_POT"
      ],
      "lifespanYears": 0.0,
      "length": 13.4,
      "type": "VEHICLETYPE_RAIL_LOCOMOTIVE",
      "descriptionId": 5419,
      "costRUB": 4300.0,
      "powerKW": 148.0,
      "emptyWeight": 19.75,
      "speed": 50.0,
      "trainGroup": "tram",
      "capacity": 101.0,
      "transportType": "RESOURCE_TRANSPORT_PASSANGER",
      "from": 1956,
      "to": 1965,
      "countryId": 39007,
      "electric": true,
      "workshopId": "3171531012",
      "modPath": "UV2"
    },
    {
      "id": "3171531012/UV3",
      "category": "workshop",
      "trainSet": [
        "3171531012/FP",
        "3171531012/UV_POT"
      ],
      "lifespanYears": 0.0,
      "length": 13.4,
      "type": "VEHICLETYPE_RAIL_LOCOMOTIVE",
      "descriptionId": 5419,
      "costRUB": 4300.0,
      "powerKW": 148.0,
      "emptyWeight": 19.75,
      "speed": 50.0,
      "trainGroup": "tram",
      "capacity": 101.0,
      "transportType": "RESOURCE_TRANSPORT_PASSANGER",
      "from": 1956,
      "to": 1965,
      "countryId": 39007,
      "electric": true,
      "workshopId": "3171531012",
      "modPath": "UV3"
    },
    {
      "id": "3171531012/UV_POT",
      "category": "workshop",
      "lifespanYears": 0.0,
      "length": 13.4,
      "type": "VEHICLETYPE_RAIL_VAGON",
      "descriptionId": 5419,
      "costRUB": 4300.0,
      "emptyWeight": 19.75,
      "speed": 50.0,
      "trainGroup": "tram",
      "capacity": 101.0,
      "transportType": "RESOURCE_TRANSPORT_PASSANGER",
      "from": 1956,
      "to": 1965,
      "countryId": 39007,
      "workshopId": "3171531012",
      "modPath": "UV_POT"
    }
  ]
}
