{
  "schemaVersion": 1,
  "workshopId": "2457740870",
  "source": "steam-workshop-config",
  "extractedAt": "2026-07-18T18:50:34+00:00",
  "buildings": [],
  "vehicles": [
    {
      "id": "2457740870/covered_gaz_next",
      "category": "workshop",
      "lifespanYears": 0.0,
      "length": 6.89,
      "type": "VEHICLETYPE_ROAD",
      "descriptionId": 5322,
      "costRUB": 8300.0,
      "capacity": 5.0,
      "transportType": "RESOURCE_TRANSPORT_COVERED",
      "speed": 110.0,
      "powerKW": 109.0,
      "emptyWeight": 8.0,
      "from": 2014,
      "roadRecipeBranch": "ordinary",
      "workshopId": "2457740870",
      "modPath": "covered_gaz_next"
    },
    {
      "id": "2457740870/gravel_gz_next",
      "category": "workshop",
      "lifespanYears": 0.0,
      "length": 6.89,
      "type": "VEHICLETYPE_ROAD",
      "descriptionId": 5322,
      "costRUB": 8300.0,
      "capacity": 5.0,
      "transportType": "RESOURCE_TRANSPORT_GRAVEL",
      "speed": 110.0,
      "powerKW": 109.0,
      "emptyWeight": 8.0,
      "from": 2014,
      "roadRecipeBranch": "ordinary",
      "workshopId": "2457740870",
      "modPath": "gravel_gz_next"
    },
    {
      "id": "2457740870/open_gaz_next",
      "category": "workshop",
      "lifespanYears": 0.0,
      "length": 6.89,
      "type": "VEHICLETYPE_ROAD",
      "descriptionId": 5322,
      "costRUB": 8300.0,
      "capacity": 5.0,
      "transportType": "RESOURCE_TRANSPORT_OPEN",
      "speed": 110.0,
      "powerKW": 109.0,
      "emptyWeight": 8.0,
      "from": 2014,
      "roadRecipeBranch": "ordinary",
      "workshopId": "2457740870",
      "modPath": "open_gaz_next"
    },
    {
      "id": "2457740870/refrig_gaz_next",
      "category": "workshop",
      "lifespanYears": 0.0,
      "length": 6.89,
      "type": "VEHICLETYPE_ROAD",
      "descriptionId": 5322,
      "costRUB": 8300.0,
      "capacity": 5.0,
      "transportType": "RESOURCE_TRANSPORT_COOLER",
      "speed": 110.0,
      "powerKW": 109.0,
      "emptyWeight": 8.0,
      "from": 2014,
      "roadRecipeBranch": "ordinary",
      "workshopId": "2457740870",
      "modPath": "refrig_gaz_next"
    }
  ]
}
